[
    {
        "pro_id": "00002",
        "client_name": "Vast Technologies",
        "domain": "https://www.vatechnologies.com",
        "category": "Ecommerce",
        "pro_status": "Last Testing Stage - Deadline 25th March",
        "progress": "1",
        "pro_logo": "https://fakeimg.pl/100x100"
    },
    {
        "pro_id": "00003",
        "client_name": "RK Builder",
        "domain": "https://www.vatechnologies.com",
        "category": "Ecommerce",
        "pro_status": "Last Testing Stage - Deadline 25th March",
        "progress": "2",
        "pro_logo": "https://fakeimg.pl/100x150"
    },
    {
        "pro_id": "00004",
        "client_name": "Vast Informatics",
        "domain": "https://www.vatechnologies.com",
        "category": "Ecommerce",
        "pro_status": "Last Testing Stage - Deadline 25th March",
        "progress": "1",
        "pro_logo": "https://fakeimg.pl/100x100"
    },
    {
        "pro_id": "00005",
        "client_name": "Super International",
        "domain": "https://www.vatechnologies.com",
        "category": "Ecommerce",
        "pro_status": "Last Testing Stage - Deadline 25th March",
        "progress": "3",
        "pro_logo": "https://fakeimg.pl/100x100"
    },
    {
        "pro_id": "00006",
        "client_name": "WayBig India",
        "domain": "https://www.vatechnologies.com",
        "category": "Ecommerce",
        "pro_status": "Last Testing Stage - Deadline 25th March",
        "progress": "4",
        "pro_logo": "https://fakeimg.pl/100x100"
    }
]